de2_1/__init__.py
de2_1/main.py
de2_1-0.3.1.dist-info/METADATA
de2_1-0.3.1.dist-info/WHEEL
de2_1-0.3.1.dist-info/RECORD
