Metadata-Version: 2.1
Name: de2-1
Version: 0.3.1
Summary: Turing college de2_1 sprint submission. FINAl working version
Author: JociusTa
Author-email: tautvydasjocius@live.com
Requires-Python: >=3.11,<4.0
Classifier: Programming Language :: Python :: 3
Classifier: Programming Language :: Python :: 3.11
Requires-Dist: numpy (>=1.24.3,<2.0.0)
Requires-Dist: requests (>=2.31.0,<3.0.0)
